{
  "imageUrl": "img/projects/a-new-townhouse-in-the-appalachian-mountains.jpg",
  "name": "A new townhouse in the Appalachian mountains",
  "snippet": "Enjoy a refreshing time amidst the monumental Appalachian mountains, in a townhouse that will host the most luxurious holiday for you and your family!",
  "description": "This home has been updated and is neat and clean. Open concept floor plan. Large deck perfect for entertaining. Easy to get to. 50 ft of frontage with a concrete seawall to ensure you maintain your property over the years. Large living areas for entertaining year round. If you have wanted to live on the lake, don't let this gem pass you by without taking a look. All measurements are approximate, BATVAI. Bring your offers, and start your summer right. Immediate occupancy so you can move right in. Motivated seller.",
  "price": "7640",
  "images": [
    "img/projects/yahoo's-data-center.jpg",
    "img/projects/yahoo's-data-center.jpg"
  ]
}